CHANGELOG.rst
LICENSE.txt
MANIFEST.in
README.rst
requirements.txt
setup.py
awscli_cwlogs.egg-info/PKG-INFO
awscli_cwlogs.egg-info/SOURCES.txt
awscli_cwlogs.egg-info/dependency_links.txt
awscli_cwlogs.egg-info/requires.txt
awscli_cwlogs.egg-info/top_level.txt
cwlogs/__init__.py
cwlogs/filter.py
cwlogs/kvstore.py
cwlogs/parser.py
cwlogs/pull.py
cwlogs/push.py
cwlogs/retry.py
cwlogs/threads.py
cwlogs/utils.py
cwlogs/examples/logs/filter.rst
cwlogs/examples/logs/pull.rst
cwlogs/examples/logs/push.rst