Metadata-Version: 1.1
Name: awscli-cwlogs
Version: 1.3.3
Summary: AWSCLI CloudWatch Logs plugin
Home-page: http://aws.amazon.com/cli/
Author: Amazon
Author-email: UNKNOWN
License: Apache License 2.0
Platform: UNKNOWN
Classifier: Development Status :: 5 - Production/Stable
Classifier: Intended Audience :: Developers
Classifier: Intended Audience :: System Administrators
Classifier: Natural Language :: English
Classifier: License :: OSI Approved :: Apache Software License
Classifier: Programming Language :: Python
Classifier: Programming Language :: Python :: 2.6
Classifier: Programming Language :: Python :: 2.7
Classifier: Programming Language :: Python :: 3
Classifier: Programming Language :: Python :: 3.3
